{"continu": 1, "keep": 1, "break": 1, "compton": 1, "exist": 1, "pig": 1, "brain": 1, "experi": 1, "decapit": 1, "cortner": 2, "advic": 1, "creatur": 1, "find": 1, "bride": 1, "without": 1, "need": 1, "guinea": 1, "unsuccess": 1, "one": 1, "less": 1, "meanwhil": 1, "basement": 1, "automobil": 1, "disfigur": 1, "perform": 1, "accid": 1, "manag": 1, "bodi": 2, "upon": 1, "hidden": 1, "bill": 3, "call": 1, "aliv": 1, "settl": 1, "experiment": 1, "fianc\u00e3": 1, "want": 1, "loos": 1, "father": 1, "model": 1, "also": 1, "dori": 1, "human": 1, "surgeri": 1, "jan": 2, "surgeon": 1, "powel": 1, "author": 1, "glamor": 1, "new": 1, "facial": 1}