{"over": 1, "year": 1, "shenanigan": 1, "fan": 1, "amor": 1, "thwart": 1, "gard": 1, "chao": 1, "around": 1, "behind": 1, "old": 1, "egocentr": 1, "concert": 1, "put": 1, "pianist": 1, "pursu": 1, "val": 2, "utter": 1, "york": 1, "citi": 2, "two": 1, "hilari": 1, "harass": 1, "orient": 1, "mother": 1, "sexual": 1, "gil": 1, "leav": 1, "henri": 2, "scene": 1, "avant": 1, "afternoon": 1, "promiscu": 1, "chase": 1, "girl": 2, "appear": 1, "mad": 1, "marri": 1, "stop": 1, "liaison": 1, "new": 1, "woman": 1}