{"miracul": 1, "year": 1, "crusti": 1, "could": 1, "becom": 1, "coney": 1, "life": 2, "know": 1, "deal": 1, "manner": 1, "thing": 1, "visit": 1, "join": 1, "georg": 1, "make": 1, "intellig": 1, "teach": 1, "find": 1, "forc": 1, "navi": 4, "island": 1, "hermit": 1, "abil": 1, "alli": 1, "limpet": 1, "one": 1, "fish": 2, "later": 1, "water": 1, "mid": 1, "dolphin": 1, "friend": 2, "activ": 1, "among": 1, "thick": 1, "help": 1, "secret": 1, "pretti": 1, "henri": 3, "crab": 1, "use": 1, "mild": 1, "creat": 1, "love": 2, "locat": 1, "fall": 1, "nazi": 1, "boat": 1, "bookkeep": 1, "rate": 1, "weapon": 2, "stickl": 1, "also": 2, "lay": 1, "get": 1, "german": 1, "may": 1, "meek": 1, "passion": 1, "wish": 1, "1941": 1, "ladyfish": 1, "sink": 1, "would": 2, "new": 2}