{"beset": 1, "minut": 2, "realiz": 1, "almost": 1, "set": 2, "dead": 1, "life": 1, "judi": 2, "seem": 1, "young": 1, "visit": 1, "take": 1, "soon": 1, "join": 1, "creatur": 1, "door": 1, "dissens": 1, "situat": 1, "window": 1, "grim": 1, "around": 1, "deterior": 1, "barbra": 3, "abandon": 1, "need": 1, "gas": 1, "report": 1, "surpris": 1, "cooper": 2, "helen": 1, "peopl": 1, "basement": 1, "coupl": 1, "immedi": 1, "lessen": 1, "return": 1, "howev": 1, "tom": 1, "farm": 1, "manag": 1, "hide": 1, "upon": 1, "cemeteri": 1, "sudden": 1, "best": 1, "want": 1, "harri": 2, "remot": 1, "father": 1, "secur": 1, "charg": 1, "grave": 1, "get": 1, "johnni": 1, "chanc": 1, "night": 1, "ben": 3, "news": 1, "refug": 1, "stop": 1, "away": 1, "walk": 1, "surviv": 1, "zombi": 1, "everywher": 1, "hous": 2}