{"cano": 1, "keep": 1, "sled": 1, "told": 1, "studi": 1, "strong": 1, "speak": 1, "spot": 1, "anim": 2, "rosi": 3, "tyler": 9, "two": 2, "togeth": 1, "miss": 1, "tourism": 1, "dog": 1, "local": 1, "travel": 3, "suspect": 1, "wolv": 7, "argument": 1, "assign": 1, "eat": 3, "soon": 1, "mice": 1, "georg": 1, "carib": 1, "attack": 1, "nervous": 1, "reduct": 1, "research": 1, "herd": 1, "wilder": 1, "pilot": 2, "explor": 1, "extrem": 1, "save": 1, "kill": 1, "translat": 1, "pack": 1, "three": 2, "camp": 1, "see": 2, "organ": 1, "learn": 2, "diseas": 1, "decid": 1, "find": 5, "hunter": 2, "ootek": 5, "govern": 2, "shelter": 1, "return": 2, "friend": 1, "alon": 1, "call": 1, "cold": 1, "initi": 1, "respons": 2, "reckless": 1, "stay": 1, "prove": 2, "suppli": 2, "trio": 1, "take": 1, "offspr": 2, "discov": 1, "plan": 1, "examin": 2, "angelin": 1, "left": 1, "popul": 1, "build": 1, "caribou": 3, "say": 1, "english": 1, "mike": 4, "excrement": 1, "area": 1, "bone": 1, "arctic": 1, "believ": 1}