{"comeback": 1, "band": 1, "fan": 1, "film": 1, "profound": 1, "spinal": 1, "stoneheng": 1, "tour": 1, "power": 1, "british": 1, "maker": 1, "tap": 2, "attempt": 1, "head": 1, "follow": 1, "heavi": 1, "eighteen": 1, "culmin": 1, "pivot": 1, "inch": 1, "perform": 1, "documentari": 1, "stage": 1, "high": 1, "group": 1, "rock": 1, "crisi": 1, "1982": 1, "prop": 1, "candid": 1, "american": 1, "music": 1, "metal": 1, "infam": 1, "also": 1, "lyric": 1, "interspers": 1, "affair": 1, "accompani": 1, "result": 1, "toward": 1, "legendari": 1}