{"lotney": 1, "set": 1, "chunk": 1, "mikey": 3, "unless": 1, "jake": 1, "cours": 2, "brother": 1, "rais": 1, "move": 1, "decid": 1, "place": 1, "data": 1, "find": 1, "lawrenc": 1, "famili": 1, "wang": 1, "cohen": 1, "one": 1, "quit": 1, "fortun": 1, "stefani": 1, "brandon": 2, "neighborhood": 2, "andrea": 1, "steinbrenn": 1, "carmichael": 1, "sever": 1, "build": 1, "disfigur": 1, "sloth": 2, "befriend": 1, "friend": 1, "construct": 1, "doubt": 1, "enough": 1, "upon": 1, "restaur": 1, "franci": 1, "hidden": 1, "treasur": 3, "gooni": 2, "prepar": 1, "mouth": 1, "call": 1, "son": 1, "money": 1, "clark": 1, "cavern": 2, "want": 1, "mama": 1, "map": 1, "quest": 1, "fratelli": 4, "fame": 1, "save": 1, "help": 1, "whose": 1, "entranc": 1, "evil": 1, "stef": 1, "hope": 1, "develop": 1, "golf": 2, "stumbl": 1, "walsh": 2, "eye": 1, "willi": 1, "stop": 1, "richard": 1, "thief": 1, "andi": 1, "devereaux": 1}