{"year": 1, "keep": 1, "luck": 1, "chapel": 1, "film": 1, "immol": 1, "church": 1, "young": 1, "interrupt": 1, "moment": 1, "jona": 3, "four": 1, "hamilton": 1, "thirti": 1, "basement": 1, "1957": 1, "coupl": 1, "later": 1, "spot": 1, "student": 1, "getaway": 1, "back": 2, "priest": 1, "togeth": 1, "slash": 1, "high": 1, "school": 1, "unfortun": 1, "enjoy": 1, "group": 1, "carri": 1, "seat": 1, "secret": 1, "prom": 3, "loos": 1, "father": 2, "seclud": 1, "lock": 1, "tradit": 1, "lover": 1, "car": 1, "get": 1, "hideout": 1, "night": 3, "begin": 1, "romant": 1, "chosen": 1, "would": 1, "drug": 1}