{"continu": 1, "shoot": 1, "crime": 1, "isol": 1, "robert": 1, "attent": 1, "booth": 1, "michael": 2, "barbara": 1, "threaten": 1, "daughter": 2, "conveni": 1, "two": 1, "retir": 1, "fria": 1, "jam": 1, "goe": 2, "fen": 2, "william": 3, "los": 1, "proceed": 1, "paul": 1, "rage": 1, "traffic": 1, "destabil": 1, "chang": 2, "detect": 1, "pay": 1, "wife": 1, "follow": 1, "apart": 1, "estrang": 1, "along": 1, "last": 1, "work": 1, "man": 1, "owner": 1, "chan": 1, "agustin": 1, "weapon": 1, "nut": 1, "prendergast": 1, "store": 1, "car": 2, "stop": 2, "angel": 1, "see": 1, "gang": 1, "shop": 1, "react": 1, "decid": 1, "place": 1, "mister": 1, "basebal": 1, "sergeant": 1, "martin": 1, "eddi": 1, "coke": 1, "meanwhil": 1, "journey": 1, "rodriguez": 1, "hershey": 1, "call": 1, "tri": 2, "crash": 1, "day": 2, "respons": 1, "joey": 1, "duval": 1, "hope": 1, "birthday": 1, "walk": 2, "lee": 1, "gangster": 2, "hous": 1, "wave": 1, "gym": 1, "break": 1, "breakdown": 1, "drink": 1, "take": 1, "way": 1, "bag": 1, "injustic": 1, "singer": 1, "give": 1, "bat": 2, "hit": 1, "leav": 1, "foster": 1, "hunt": 1, "dougla": 1, "get": 2, "phone": 2, "believ": 1}