{"dale": 4, "happen": 1, "band": 1, "learn": 1, "told": 1, "visit": 1, "ray": 1, "goofbal": 1, "discov": 1, "soon": 1, "sugar": 1, "find": 3, "writer": 1, "aleck": 1, "lawyer": 1, "lawrenc": 1, "around": 1, "one": 3, "follow": 1, "home": 1, "kid": 2, "road": 1, "question": 1, "back": 1, "tell": 2, "escap": 1, "son": 3, "rock": 1, "call": 1, "hit": 1, "hotel": 1, "room": 1, "use": 1, "day": 2, "love": 1, "jack": 4, "father": 2, "struck": 1, "teamwork": 1, "also": 1, "stori": 1, "girlfriend": 2, "must": 1, "drunk": 1, "real": 2, "smart": 1, "bring": 2, "enter": 1, "meet": 2, "sacramento": 1, "depress": 1, "putley": 1}