{"marriag": 1, "attent": 1, "error": 1, "fli": 1, "infect": 1, "undisput": 1, "perfect": 1, "york": 1, "two": 1, "high": 1, "thornton": 1, "nick": 4, "slip": 1, "room": 1, "pace": 1, "must": 1, "zone": 1, "let": 1, "regain": 1, "workplac": 1, "reput": 1, "hotspot": 1, "thrown": 1, "traffic": 1, "one": 1, "wife": 1, "time": 1, "upmanship": 1, "work": 1, "tin": 1, "wander": 1, "impress": 1, "boy": 1, "rule": 1, "vicki": 1, "pure": 1, "bell": 1, "life": 1, "tens": 1, "held": 1, "air": 1, "falzon": 1, "find": 1, "record": 1, "need": 1, "control": 3, "status": 1, "lead": 1, "lewi": 1, "job": 1, "span": 1, "thrive": 1, "saniti": 2, "reckless": 1, "short": 1, "transfer": 1, "fast": 2, "push": 1, "break": 1, "wed": 1, "way": 1, "quiet": 1, "king": 1, "repair": 1, "bed": 1, "hold": 1, "game": 1, "town": 1, "russel": 2, "say": 1, "leav": 1, "cusack": 1, "plane": 1, "quo": 1, "get": 1, "live": 1, "least": 1, "complet": 1, "shatter": 1, "new": 2}