{"keep": 1, "could": 1, "maurier": 2, "move": 1, "doom": 1, "appreci": 1, "member": 1, "feel": 2, "look": 1, "peopl": 1, "process": 2, "frohman": 1, "threaten": 1, "daughter": 1, "pressur": 1, "children": 1, "overbear": 1, "recent": 1, "two": 1, "flow": 1, "potenti": 1, "peter": 5, "idea": 1, "dog": 1, "latest": 1, "abl": 1, "juic": 1, "alway": 1, "impresario": 1, "welcom": 1, "quick": 1, "bring": 1, "let": 1, "barri": 2, "fate": 1, "partak": 1, "befal": 1, "someth": 1, "disciplin": 1, "playwright": 1, "gone": 1, "renown": 1, "next": 1, "georg": 1, "review": 1, "write": 1, "four": 1, "one": 3, "wife": 1, "product": 1, "griev": 1, "less": 1, "llewelyn": 4, "posit": 1, "imagin": 1, "davi": 4, "viabl": 1, "failur": 2, "impos": 1, "pan": 1, "replac": 1, "mother": 1, "jame": 8, "want": 1, "relationship": 1, "maintain": 1, "father": 1, "mari": 1, "still": 2, "thus": 1, "london": 1, "play": 4, "stumbl": 1, "six": 1, "boy": 2, "regard": 1, "unmarri": 1, "charl": 2, "integr": 1, "backward": 1, "woman": 1, "see": 2, "outing": 1, "becom": 3, "life": 1, "effort": 1, "knew": 1, "impedi": 1, "place": 1, "self": 1, "theater": 1, "eventu": 1, "famili": 3, "come": 1, "need": 2, "creativ": 1, "husband": 2, "friend": 1, "among": 2, "upon": 1, "son": 1, "call": 1, "help": 1, "1903": 1, "day": 1, "friendship": 1, "adolesc": 1, "amalgam": 1, "respons": 1, "also": 1, "widow": 1, "hope": 1, "garner": 1, "walk": 1, "author": 1, "shell": 1, "would": 1, "import": 1, "even": 1, "case": 1, "take": 1, "deceas": 1, "base": 2, "plan": 1, "realiti": 1, "within": 1, "biggest": 1, "larg": 2, "obstacl": 1, "emma": 1, "like": 1, "sylvia": 6, "step": 1, "foster": 1, "similar": 1, "immin": 1, "third": 1, "late": 1, "anoth": 4, "live": 3, "part": 2, "may": 1, "mount": 1, "unmount": 1}