{"elit": 1, "pound": 1, "edward": 1, "underworld": 1, "cocain": 1, "pal": 1, "old": 1, "threaten": 1, "daughter": 1, "whole": 1, "two": 1, "tell": 1, "retir": 1, "best": 1, "miss": 1, "skill": 1, "dealer": 1, "cross": 1, "mix": 1, "top": 1, "draw": 1, "busi": 3, "mafia": 1, "goe": 1, "penalti": 1, "england": 1, "ecstasi": 1, "matter": 1, "assign": 1, "success": 1, "serbian": 1, "gossip": 1, "lifetim": 1, "price": 1, "reveal": 1, "chang": 1, "cake": 2, "one": 1, "time": 1, "back": 1, "jimmi": 2, "construct": 1, "modern": 1, "last": 2, "level": 1, "tough": 1, "rise": 1, "escap": 1, "refer": 1, "savvi": 1, "grade": 1, "love": 1, "respect": 2, "intern": 1, "doubl": 1, "rule": 1, "ultim": 1, "gang": 1, "rich": 1, "know": 1, "princess": 1, "complic": 1, "code": 1, "place": 1, "find": 1, "layer": 2, "boss": 1, "seri": 1, "famili": 1, "titl": 1, "job": 1, "run": 1, "among": 1, "hand": 1, "endur": 1, "call": 1, "worth": 1, "paper": 1, "player": 1, "million": 1, "tammi": 1, "drug": 1, "line": 1, "anyon": 1, "make": 1, "ring": 1, "big": 1, "plan": 1, "earli": 1, "ryder": 1, "charlott": 1, "earn": 1, "howev": 1, "interest": 1, "socialit": 1, "brutal": 1, "use": 1, "trust": 1, "long": 1, "power": 1}