{"legitim": 1, "becom": 2, "plot": 1, "puss": 1, "envious": 1, "decid": 1, "pass": 1, "join": 1, "find": 1, "boot": 1, "king": 2, "fiona": 2, "meanwhil": 1, "immedi": 1, "return": 1, "villain": 1, "ambiti": 1, "coup": 1, "howev": 1, "friend": 1, "distant": 1, "belov": 1, "kingdom": 1, "swamp": 1, "abl": 1, "heir": 1, "princ": 1, "\u00e9tat": 1, "arti": 1, "donkey": 1, "father": 1, "fairytal": 1, "shrek": 2, "clumsi": 1, "successor": 1, "pregnant": 1, "far": 2, "away": 2, "throne": 1, "charm": 1, "new": 1, "hous": 1}