{"set": 1, "plot": 1, "await": 1, "rippner": 1, "young": 1, "move": 1, "fear": 1, "flight": 2, "killer": 1, "would": 1, "homeland": 1, "coerc": 1, "board": 1, "target": 1, "fli": 2, "pin": 1, "handsom": 1, "posit": 1, "villain": 1, "offici": 1, "trap": 1, "reisert": 1, "lisa": 3, "upon": 1, "got": 1, "resort": 1, "work": 1, "creepi": 1, "middl": 1, "assassin": 1, "man": 2, "name": 2, "noth": 1, "jackson": 1, "miami": 1, "use": 1, "secur": 1, "father": 1, "plane": 1, "pre": 1, "luxuri": 1, "stori": 1, "play": 1, "heroin": 1, "arrang": 1, "eye": 1, "night": 1, "phone": 1, "terror": 1, "red": 1, "charm": 1, "resourc": 1, "advantag": 1, "hate": 1}