{"perman": 1, "supernatur": 1, "decad": 1, "skeptic": 1, "check": 2, "place": 1, "find": 1, "writer": 1, "spend": 1, "sue": 1, "phenomena": 1, "write": 2, "cynic": 1, "graveyard": 1, "object": 1, "might": 1, "one": 1, "olin": 2, "curs": 1, "evalu": 1, "posess": 1, "book": 2, "enslin": 1, "final": 2, "threaten": 1, "1408": 2, "booz": 1, "fifti": 1, "howev": 1, "offer": 1, "allow": 1, "york": 1, "dolphin": 1, "manag": 1, "gerald": 1, "expens": 1, "promis": 1, "request": 1, "reluct": 1, "aliv": 1, "hotel": 3, "latest": 1, "room": 5, "unavail": 1, "leav": 1, "never": 1, "mike": 2, "travel": 1, "guest": 3, "usual": 1, "haunt": 1, "upgrad": 1, "night": 2, "debunk": 1, "relat": 1, "death": 1, "later": 1, "los": 1, "mysteri": 1, "new": 1, "angel": 1}