{"realiz": 1, "throw": 1, "orphan": 1, "unravel": 1, "adopt": 1, "rais": 2, "take": 1, "sim\u00f3n": 4, "disappear": 1, "decid": 1, "cater": 1, "invis": 1, "laura": 6, "parti": 2, "old": 1, "invit": 1, "product": 1, "presenc": 1, "mask": 1, "five": 1, "look": 1, "feel": 1, "peopl": 1, "see": 1, "imagin": 1, "later": 2, "children": 1, "husband": 1, "tell": 1, "friend": 2, "togeth": 1, "former": 2, "son": 1, "month": 1, "activ": 1, "tri": 2, "carlo": 1, "cabin": 1, "team": 1, "parapsychologist": 1, "also": 1, "busi": 1, "persuad": 1, "disabl": 1, "reopen": 1, "boy": 1, "orphanag": 3, "mysteri": 2, "hous": 2, "believ": 1}