{"expel": 1, "set": 1, "allur": 1, "hard": 1, "summarili": 1, "host": 1, "figur": 1, "darlingson": 1, "rais": 1, "take": 2, "misfit": 1, "move": 1, "make": 1, "great": 1, "plus": 1, "place": 1, "find": 3, "self": 1, "famili": 1, "parti": 1, "fox": 1, "old": 1, "one": 1, "shelley": 2, "member": 1, "succeed": 1, "makeov": 1, "pledg": 2, "final": 1, "job": 1, "interest": 1, "zeta": 1, "27th": 1, "blossom": 1, "lose": 1, "unfortun": 1, "mother": 1, "month": 1, "sabotag": 1, "mansion": 1, "playboy": 1, "act": 1, "happi": 1, "mean": 1, "girl": 2, "soror": 2, "birthday": 1, "smart": 1, "boy": 1, "desper": 1, "lack": 1, "orphanag": 1, "everywher": 1, "hous": 3}