{"keep": 1, "band": 1, "zealand": 1, "even": 1, "organ": 1, "shop": 1, "manipul": 1, "georgia": 3, "immatur": 1, "cours": 1, "mind": 1, "seem": 1, "brother": 2, "dump": 1, "move": 1, "unlik": 1, "jas": 1, "classmat": 1, "dave": 1, "ever": 1, "ignor": 1, "besot": 1, "famili": 1, "retain": 1, "hot": 1, "laugh": 1, "chang": 1, "parti": 1, "digniti": 1, "eldest": 1, "opportun": 1, "jem": 1, "hotti": 1, "cat": 1, "career": 1, "kiss": 1, "grand": 1, "later": 1, "daughter": 1, "brat": 1, "tom": 1, "consid": 1, "angus": 1, "run": 1, "pupil": 1, "friend": 1, "given": 1, "cruelti": 1, "hunki": 1, "crazi": 1, "best": 2, "mother": 1, "lindsay": 1, "call": 1, "help": 1, "peter": 1, "haughti": 1, "engin": 1, "groceri": 1, "father": 1, "stiff": 1, "fluffi": 1, "reconsid": 1, "thus": 1, "eastbourn": 1, "flirt": 1, "london": 1, "birthday": 1, "dylan": 1, "interior": 1, "complet": 1, "dyer": 1, "appar": 1, "robbi": 2, "new": 1, "decor": 1}