{"absenc": 1, "thing": 1, "conform": 2, "brother": 1, "around": 1, "fit": 3, "old": 1, "institut": 1, "look": 1, "feel": 1, "mischief": 1, "competit": 1, "threaten": 2, "dancer": 1, "student": 1, "tyler": 1, "audit": 2, "west": 1, "best": 1, "teen": 1, "conflict": 1, "fact": 1, "act": 2, "vandal": 1, "texa": 1, "especi": 1, "bring": 1, "sure": 2, "collin": 2, "andi": 9, "expuls": 1, "includ": 1, "unless": 1, "tuck": 2, "pass": 1, "age": 1, "one": 1, "follow": 1, "art": 1, "director": 1, "shadow": 1, "convinc": 2, "judgment": 1, "mother": 1, "kick": 1, "want": 1, "love": 1, "parent": 1, "led": 1, "respect": 1, "chase": 2, "care": 1, "polic": 1, "ultim": 1, "brilliant": 1, "learn": 1, "life": 2, "gage": 1, "figur": 1, "crew": 5, "misfit": 2, "turn": 1, "neighborhood": 1, "friend": 3, "among": 1, "school": 5, "danc": 5, "notori": 1, "start": 1, "tri": 4, "gain": 1, "baltimor": 1, "msa": 4, "relat": 1, "blake": 5, "410": 4, "maryland": 1, "clean": 1, "think": 1, "send": 1, "harder": 1, "way": 2, "anyon": 1, "due": 1, "within": 1, "associ": 3, "illeg": 1, "public": 1, "rehears": 1, "hide": 1, "like": 1, "end": 2, "better": 1, "use": 1, "street": 5, "entri": 1, "live": 3, "death": 1, "particip": 1, "sarah": 2, "either": 1, "new": 3}