{"across": 1, "solac": 1, "spend": 1, "vehicl": 1, "guard": 1, "villag": 2, "claudia": 1, "wasteland": 1, "anim": 1, "daughter": 1, "water": 1, "carri": 1, "skill": 1, "destroy": 1, "gentl": 1, "must": 1, "america": 1, "person": 1, "year": 1, "beat": 1, "clear": 1, "reveal": 1, "small": 1, "post": 1, "apocalypt": 1, "press": 1, "convinc": 1, "last": 1, "mother": 1, "societi": 1, "man": 3, "want": 1, "wander": 1, "girl": 1, "westward": 1, "impress": 1, "lover": 1, "north": 1, "violent": 1, "formid": 1, "solara": 1, "see": 1, "rule": 1, "saw": 1, "gang": 2, "blind": 1, "life": 1, "declin": 1, "place": 1, "find": 2, "good": 1, "first": 1, "book": 4, "eli": 7, "surviv": 1, "carnegi": 4, "advanc": 1, "prove": 2, "hous": 1, "suppli": 1, "send": 2, "take": 2, "make": 1, "trade": 1, "within": 1, "drifter": 1, "thirti": 1, "whilst": 1, "view": 1, "howev": 1, "seek": 1, "offer": 1, "reach": 1, "better": 1, "sleep": 1, "fight": 1, "hunt": 1, "mobster": 1, "close": 1, "least": 1, "night": 1, "foe": 1, "uniqu": 1, "power": 1}