{"francisco": 1, "film": 1, "life": 1, "young": 1, "ginsberg": 1, "artist": 1, "trial": 2, "moment": 1, "interwoven": 1, "find": 1, "birth": 1, "hybrid": 1, "countercultur": 1, "recount": 1, "dramat": 1, "howl": 1, "true": 1, "1957": 1, "reaction": 1, "poem": 1, "put": 1, "anim": 1, "thread": 1, "obscen": 1, "echo": 1, "event": 1, "dark": 1, "societi": 1, "use": 1, "san": 1, "style": 1, "american": 1, "led": 1, "surreal": 1, "tumultu": 1, "three": 2, "coalesc": 1, "masterpiec": 1, "allen": 1, "voic": 1}