{"contract": 1, "shoulder": 1, "stolen": 1, "shop": 1, "bullet": 1, "life": 1, "crime": 1, "network": 1, "marcus": 1, "robert": 1, "soon": 1, "execut": 1, "loui": 3, "wait": 1, "greeli": 2, "form": 2, "unlik": 1, "contact": 1, "betray": 1, "ronni": 1, "discov": 1, "kwon": 1, "detect": 2, "come": 1, "lawyer": 1, "entrepreneur": 1, "murder": 1, "evid": 1, "hank": 1, "washington": 1, "bonomo": 1, "meanwhil": 1, "partnership": 1, "hire": 1, "bar": 1, "baptist": 1, "depart": 1, "earl": 1, "daughter": 1, "blanchard": 1, "dirti": 2, "shot": 1, "corrupt": 1, "men": 1, "two": 1, "lisa": 1, "jimmi": 5, "payment": 1, "mercenari": 1, "jame": 1, "taylor": 3, "hit": 1, "hotel": 1, "room": 1, "keegan": 1, "bobo": 1, "save": 1, "cop": 1, "morel": 1, "remov": 1, "nurs": 1, "bring": 1, "intermedi": 1, "polic": 2, "orlean": 2, "stab": 1, "investig": 2, "new": 2, "nkomo": 1}