{"rogu": 1, "across": 1, "race": 1, "includ": 1, "enemi": 1, "world": 2, "supernatur": 1, "caus": 1, "armi": 1, "moment": 1, "creatur": 1, "kind": 1, "separ": 1, "killer": 1, "slay": 1, "vicious": 1, "hunter": 1, "centuri": 2, "kaulder": 4, "amongst": 1, "spent": 1, "wife": 1, "follow": 1, "today": 1, "curs": 1, "astound": 1, "one": 2, "forev": 1, "lost": 1, "process": 1, "determin": 1, "hold": 1, "yearn": 1, "daughter": 1, "howev": 1, "seek": 1, "manag": 1, "belov": 1, "modern": 1, "reveng": 1, "upon": 1, "unbeknownst": 1, "secret": 2, "witch": 5, "battl": 2, "unnatur": 1, "afterlif": 1, "globe": 1, "love": 1, "hunt": 1, "intent": 1, "valiant": 1, "long": 1, "still": 1, "resurrect": 1, "unleash": 1, "black": 1, "queen": 3, "epic": 1, "live": 1, "remain": 1, "human": 1, "death": 2, "decim": 1, "mani": 1, "surviv": 1, "warrior": 1, "right": 1, "immort": 1, "power": 1}