{"involv": 1, "vacat": 1, "freak": 1, "face": 1, "learn": 1, "think": 2, "know": 1, "soon": 3, "realize": 1, "discov": 1, "turn": 2, "swim": 1, "form": 1, "shark": 3, "attack": 1, "come": 2, "one": 1, "sun": 1, "lead": 1, "problem": 1, "speci": 1, "wound": 1, "lurk": 1, "transport": 1, "lake": 1, "perfect": 1, "immedi": 1, "imagin": 1, "seven": 1, "water": 2, "accid": 2, "friend": 3, "tabl": 1, "primal": 1, "rip": 1, "ski": 1, "group": 1, "help": 1, "activ": 1, "fun": 1, "suit": 1, "boat": 1, "never": 1, "trust": 1, "sara": 1, "fate": 1, "signal": 1, "colleg": 1, "weekend": 1, "get": 1, "pack": 1, "arm": 1, "star": 1, "phone": 1, "footbal": 1, "would": 1, "malik": 1, "hous": 1, "believ": 1}