{"empir": 1, "across": 2, "inabl": 1, "organ": 1, "evan": 1, "elit": 1, "dead": 1, "full": 1, "countri": 1, "aid": 1, "brian": 1, "crew": 1, "command": 1, "way": 1, "dom": 3, "ruthless": 1, "hobb": 2, "outmatch": 1, "thought": 1, "hero": 1, "make": 1, "second": 1, "reveal": 1, "famili": 1, "ask": 1, "assembl": 1, "home": 2, "100": 1, "left": 2, "forev": 1, "meanwhil": 1, "lethal": 1, "track": 1, "return": 2, "toppl": 1, "whole": 1, "rio": 1, "crimin": 1, "rodriguez": 1, "outfit": 1, "payment": 1, "mercenari": 1, "pardon": 1, "level": 1, "scatter": 1, "skill": 1, "incomplet": 1, "diesel": 1, "street": 1, "globe": 1, "love": 1, "whose": 1, "walker": 1, "team": 1, "johnson": 1, "mastermind": 1, "letti": 1, "london": 1, "live": 2, "heist": 1, "driver": 1, "million": 1, "stop": 1, "kingpin": 1, "sinc": 1, "lam": 1}