{"built": 1, "insur": 1, "shoot": 2, "coast": 2, "world": 2, "offic": 1, "roc": 3, "leg": 1, "clocksmith": 3, "soon": 2, "case": 1, "attend": 1, "rebuild": 1, "discov": 1, "robert": 2, "pilgrim": 1, "place": 1, "power": 1, "boss": 1, "7000": 1, "sean": 1, "ask": 1, "possibl": 1, "corpor": 1, "illeg": 1, "robot": 8, "2044": 1, "claim": 1, "wife": 1, "cleo": 1, "popul": 1, "lead": 1, "peopl": 1, "one": 1, "jacq": 6, "alter": 2, "offer": 1, "rachel": 1, "two": 1, "friend": 1, "expect": 1, "agent": 1, "call": 1, "help": 1, "bold": 1, "want": 1, "owner": 1, "automata": 1, "resolv": 1, "storm": 1, "design": 1, "secur": 1, "vaucan": 2, "charg": 1, "wallac": 3, "brothel": 1, "dupr\u00e8": 1, "modifi": 4, "respons": 1, "kill": 1, "protocol": 1, "human": 1, "live": 1, "transfer": 1, "neither": 1, "pregnant": 1, "million": 1, "surviv": 1, "harm": 1, "polic": 1, "blame": 1, "investig": 1, "meet": 1, "solar": 1, "believ": 2}