{"Title":"Dice Rules","Year":"1991","Rated":"NC-17","Released":"17 May 1991","Runtime":"88 min","Genre":"Comedy, Documentary","Director":"Jay Dubin","Writer":"Andrew Dice Clay (story), Lenny Schulman (screenplay), Andrew Dice Clay","Actors":"Andrew Dice Clay, Eddie Griffin, Sylvia Harman, Lee Lawrence","Plot":"Before he was The Diceman, he was a poor, pathetic, put-upon Jew from New York who was disrespected by everyone he came across. Everyone. Then - he got the studded vanity leather jacket--...","Language":"English","Country":"USA","Awards":"3 nominations.","Poster":"https://m.media-amazon.com/images/M/MV5BMTIzODcyNTUwNl5BMl5BanBnXkFtZTcwOTA4MjUyMQ@@._V1_SX300.jpg","Ratings":[{"Source":"Internet Movie Database","Value":"5.3/10"},{"Source":"Rotten Tomatoes","Value":"9%"}],"Metascore":"N/A","imdbRating":"5.3","imdbVotes":"561","imdbID":"tt0101726","Type":"movie","DVD":"N/A","BoxOffice":"N/A","Production":"N/A","Website":"N/A","Response":"True"}