{"Title":"Amos & Andrew","Year":"1993","Rated":"PG-13","Released":"05 Mar 1993","Runtime":"96 min","Genre":"Comedy, Crime","Director":"E. Max Frye","Writer":"E. Max Frye","Actors":"Samuel L. Jackson, Michael Lerner, Margaret Colin, Nicolas Cage","Plot":"When Andrew Sterling, a successful black urbanite writer buys a vacation home on a resort in New England the police mistake him for a burglar. After surrounding his home with armed men, Chief Tolliver realizes his mistake and to avoid the bad publicity offers a thief in his jail, Amos Odell a deal. Amos is to pretend to take Andrew prisoner and hold him for ransom but let him go and escape. Amos and Andrew suddenly realize that the Chief's problems are all gone if the two of them both die in a gun battle. The worst partnership in film history then tries to get away from the local police.","Language":"English, Spanish","Country":"USA","Awards":"N/A","Poster":"https://m.media-amazon.com/images/M/MV5BNTZhNzhmNWEtNjllOC00YjE1LWE1ZDUtYTk4MzUwZTk0Y2IyXkEyXkFqcGdeQXVyNzc5MjA3OA@@._V1_SX300.jpg","Ratings":[{"Source":"Internet Movie Database","Value":"5.7/10"},{"Source":"Rotten Tomatoes","Value":"17%"}],"Metascore":"N/A","imdbRating":"5.7","imdbVotes":"8,439","imdbID":"tt0106266","Type":"movie","DVD":"N/A","BoxOffice":"N/A","Production":"N/A","Website":"N/A","Response":"True"}