{"Title":"The Three Musketeers","Year":"1993","Rated":"PG","Released":"12 Nov 1993","Runtime":"105 min","Genre":"Action, Adventure, Comedy, Family, Romance","Director":"Stephen Herek","Writer":"Alexandre Dumas (based on the novel by), David Loughery (screenplay by)","Actors":"Charlie Sheen, Kiefer Sutherland, Chris O'Donnell, Oliver Platt","Plot":"The three best of the disbanded Musketeers - Athos, Porthos, and Aramis - join a young hotheaded would-be-Musketeer, D'Artagnan, to stop the Cardinal Richelieu's evil plot: to form an alliance with enemy England by way of the mysterious Milady. Rochefort, the Cardinal's right-hand man, announces the official disbanding of the King's Musketeers. Three, however, refuse to throw down their swords - Athos the fighter and drinker, Porthos the pirate and lover, and Aramis the priest and poet. Arriving in Paris to join the Musketeers, D'Artagnan uncovers the Cardinal's plans, and the four set out on a mission to protect King and Country.","Language":"English","Country":"Austria, UK, USA","Awards":"2 wins & 3 nominations.","Poster":"https://m.media-amazon.com/images/M/MV5BMzc4OTJlMTgtMWE5MC00MDRlLWE2MDQtYTI4ZTAzNzUyZjM2XkEyXkFqcGdeQXVyNjExODE1MDc@._V1_SX300.jpg","Ratings":[{"Source":"Internet Movie Database","Value":"6.4/10"},{"Source":"Rotten Tomatoes","Value":"28%"},{"Source":"Metacritic","Value":"43/100"}],"Metascore":"43","imdbRating":"6.4","imdbVotes":"50,062","imdbID":"tt0108333","Type":"movie","DVD":"N/A","BoxOffice":"N/A","Production":"Walt Disney Pictures, Caravan Pictures","Website":"N/A","Response":"True"}