{"Title":"Maverick","Year":"1994","Rated":"PG","Released":"20 May 1994","Runtime":"127 min","Genre":"Action, Adventure, Comedy, Thriller, Western","Director":"Richard Donner","Writer":"Roy Huggins (television series Maverick), William Goldman","Actors":"Mel Gibson, Jodie Foster, James Garner, Graham Greene","Plot":"Maverick is recreated from the character James Garner created in the 1950s TV program. Maverick is a gambler who would rather con someone than fight them. He needs an additional three thousand dollars in order to enter a Winner Take All poker game that begins in a few days. He tries to win some, tries to collect a few debts, and recover a little loot for the reward, all with a light hearted air. He joins forces with a woman gambler with a marvelous, though fake, southern accent as the two both try and enter the game.","Language":"English","Country":"USA","Awards":"Nominated for 1 Oscar. Another 1 win & 1 nomination.","Poster":"https://m.media-amazon.com/images/M/MV5BY2I1OTY2NmUtMGVlZi00NjNmLThkNTgtMjExMzRhOTM2MDJiXkEyXkFqcGdeQXVyNDk3NzU2MTQ@._V1_SX300.jpg","Ratings":[{"Source":"Internet Movie Database","Value":"7.0/10"},{"Source":"Rotten Tomatoes","Value":"66%"},{"Source":"Metacritic","Value":"62/100"}],"Metascore":"62","imdbRating":"7.0","imdbVotes":"100,113","imdbID":"tt0110478","Type":"movie","DVD":"N/A","BoxOffice":"N/A","Production":"Warner Bros., Donner/Schuler-Donner, Icon Entertainment International","Website":"N/A","Response":"True"}