{"Title":"Fall","Year":"1997","Rated":"Not Rated","Released":"20 Jun 1997","Runtime":"93 min","Genre":"Drama, Romance","Director":"Eric Schaeffer","Writer":"Eric Schaeffer","Actors":"Eric Schaeffer, Amanda De Cadenet, Rudolf Martin, Francie Swift","Plot":"Two people from completely different worlds meet by chance, thrown together as if by fate. Their attraction is immediately obvious and overwhelming. He is attracted to her beauty (she is a supermodel) and good humor; she is seduced by his charisma and honesty. With his gifts of poetry and tenderness, he opens her heart to the possibility of true love. But it takes a lot of courage to make a commitment. Is she truly in love with him? And even if she is, will she able to leave the cosmopolitan, superficial lifestyle to be with him?","Language":"English","Country":"USA","Awards":"N/A","Poster":"https://m.media-amazon.com/images/M/MV5BMGViMzBlZDEtYWQ0MC00YzBmLTg5OGUtN2E0YjMxY2UzM2FiXkEyXkFqcGdeQXVyMTQxNzMzNDI@._V1_SX300.jpg","Ratings":[{"Source":"Internet Movie Database","Value":"6.0/10"},{"Source":"Rotten Tomatoes","Value":"0%"}],"Metascore":"N/A","imdbRating":"6.0","imdbVotes":"1,671","imdbID":"tt0119098","Type":"movie","DVD":"N/A","BoxOffice":"N/A","Production":"Five Minutes Before the Miracle, Terence Michael Productions","Website":"N/A","Response":"True"}