{"Title":"Songs from the Second Floor","Year":"2000","Rated":"Not Rated","Released":"06 Oct 2000","Runtime":"98 min","Genre":"Comedy, Drama","Director":"Roy Andersson","Writer":"Roy Andersson","Actors":"Lars Nordh, Stefan Larsson, Bengt C.W. Carlsson, Torbjörn Fahlström","Plot":"A film poem inspired by the Peruvian poet César Vallejo. A story about our need for love, our confusion, greatness and smallness and, most of all, our vulnerability. It is a story with many characters, among them a father and his mistress, his youngest son and his girlfriend. It is a film about big lies, abandonment and the eternal longing for companionship and confirmation.","Language":"Swedish, Russian","Country":"Sweden, Norway, Denmark","Awards":"9 wins & 5 nominations.","Poster":"https://m.media-amazon.com/images/M/MV5BMGQ4NGQ3MjAtYWI4Mi00YTQ1LTg1NWItN2RhYWU5YmY0Yjg0XkEyXkFqcGdeQXVyNzQxNDExNTU@._V1_SX300.jpg","Ratings":[{"Source":"Internet Movie Database","Value":"7.6/10"},{"Source":"Rotten Tomatoes","Value":"89%"},{"Source":"Metacritic","Value":"77/100"}],"Metascore":"77","imdbRating":"7.6","imdbVotes":"17,393","imdbID":"tt0120263","Type":"movie","DVD":"N/A","BoxOffice":"N/A","Production":"Nordisk Film &amp; TV-Fond","Website":"N/A","Response":"True"}