{"Title":"I Am David","Year":"2003","Rated":"PG","Released":"03 Dec 2004","Runtime":"90 min","Genre":"Adventure, Drama","Director":"Paul Feig","Writer":"Anne Holm (novel), Paul Feig (screenplay)","Actors":"Ben Tibber, Jim Caviezel, Hristo Shopov, Roberto Attias","Plot":"Twelve-year-old David escapes from a Communist concentration camp with little more than a compass, a sealed letter, a loaf of bread, and instructions to carry the letter to Copenhagen, Denmark. David is thrust into the free world for the first time as he travels across Europe. His spiritual voyage of discovery, where David slowly loses his instinctive mistrust of humanity and begins to smile, share, trust and ultimately, love, addresses the cruelties, politics, and suffering of warfare while celebrating the unbreakable spirit of a child.","Language":"English","Country":"UK, USA","Awards":"8 wins & 1 nomination.","Poster":"https://m.media-amazon.com/images/M/MV5BMTc0MDI3MzgwN15BMl5BanBnXkFtZTcwOTQ2MTcyMQ@@._V1_SX300.jpg","Ratings":[{"Source":"Internet Movie Database","Value":"7.2/10"},{"Source":"Rotten Tomatoes","Value":"39%"},{"Source":"Metacritic","Value":"47/100"}],"Metascore":"47","imdbRating":"7.2","imdbVotes":"7,069","imdbID":"tt0327919","Type":"movie","DVD":"N/A","BoxOffice":"N/A","Production":"Walden Media","Website":"N/A","Response":"True"}