{"Title":"Blood Creek","Year":"2009","Rated":"R","Released":"09 Oct 2009","Runtime":"90 min","Genre":"Action, Fantasy, Horror, Thriller","Director":"Joel Schumacher","Writer":"David Kajganich","Actors":"Henry Cavill, Dominic Purcell, Emma Booth, Michael Fassbender","Plot":"In 1936, the Wollners - a German family living in rural Morgan County, West Virginia - are contacted by the Third Reich to host a visiting scholar, Professor Richard Wirth. In need of money, they accept Wirth into their home. Wirth's grand occult project seals the Wollners off from the rest of the world and makes them players in a horrifying game of survival. After 71 years, in 2007, Evan Marshall's life has stalled at twenty-five years old. Left without answers after his older brother Victor's disappearance from a camping trip near Town Creek, he has tried to move on. But when Victor returns one night, very much alive and having escaped his captors, Evan asks no questions - at his brother's request, he loads their rifles, packs up their boat and follows him back to Town Creek on a mission of revenge that will test them in every possible way...","Language":"English, German","Country":"USA, UK, Romania","Awards":"N/A","Poster":"https://m.media-amazon.com/images/M/MV5BMTkwNzMzNzA0OF5BMl5BanBnXkFtZTcwNjQ0NDM1Mw@@._V1_SX300.jpg","Ratings":[{"Source":"Internet Movie Database","Value":"5.3/10"},{"Source":"Rotten Tomatoes","Value":"43%"}],"Metascore":"N/A","imdbRating":"5.3","imdbVotes":"11,459","imdbID":"tt0450336","Type":"movie","DVD":"N/A","BoxOffice":"N/A","Production":"Gold Circle Films","Website":"N/A","Response":"True"}